{
  "9": {
    "Comfort Food": ["Chef Choice"],
    "International Station": ["Asian"]
  },
  "12": {
    "Comfort Food": ["Cheese Tortellini"],
    "Mindful": ["Lemon Garlic Baked Chicken"],
    "Sides": ["Roasted Carrots", "Roasted Red Potatoes"],
    "Soup": ["Smokey Poblano", "Chicken Noodle"],
    "International Station": ["Asian"]
  },
  "13": {
    "Comfort Food": ["Chicken Shawarma w/ Pita"],
    "Mindful": ["Gyro w/ Pita"],
    "Sides": ["Simple Green Salad", "Lemon Rice", "Tahini Sauce"],
    "Soup": ["Smokey Poblano", "Chicken Noodle"],
    "International Station": ["Asian"]
  },
  "14": {
    "Comfort Food": ["Home Made Beef Meatloaf"],
    "Mindful": ["Roast Turkey Breast"],
    "Sides": ["Roasted Carrots and Broccoli", "Mashed Potatoes"],
    "Soup": ["Smokey Poblano", "Chicken Noodle"],
    "International Station": ["Asian"]
  },
  "15": {
    "Comfort Food": ["Baked Mostaccioli"],
    "Mindful": ["Chicken Tinga"],
    "Sides": ["Azteca Corn", "Mexican Rice"],
    "Soup": ["Smokey Poblano", "Chicken Noodle"],
    "International Station": ["Asian"]
  },
  "16": {
    "Comfort Food": ["BBQ Pulled Chicken Sandwich"],
    "Mindful": ["Palak Paneer"],
    "Sides": ["Roasted Vegetables", "Yellow Rice"],
    "Soup": ["Smokey Poblano", "Chicken Noodle"],
    "International Station": ["Asian"]
  },
  "19": {
    "Comfort Food": ["Blackened Tilapia"],
    "Mindful": ["Jerk Chicken"],
    "Sides": ["Brussel Sprouts", "Scallopped Potatoes"],
    "Soup": ["Tomato Basil Bisque", "Broccoli Cheddar"],
    "International Station": ["Pasta"]
  },
  "20": {
    "Comfort Food": ["Veggie Chilaquiles"],
    "Mindful": ["Thai Chicken Stir Fry"],
    "Sides": ["Roasted Carrots", "Cilantro Lime Rice"],
    "Soup": ["Tomato Basil Bisque", "Broccoli Cheddar"],
    "International Station": ["Pasta"]
  },
  "21": {
    "Comfort Food": ["Chicken Tettrazini"],
    "Mindful": ["Tortilla Crusted Tilapia"],
    "Sides": ["Sugar Snap Peas", "Orzo"],
    "Soup": ["Tomato Basil Bisque", "Broccoli Cheddar"],
    "International Station": ["Pasta"]
  },
  "22": {
    "Comfort Food": ["Coconut Curry w/ Rice"],
    "Mindful": ["Baked Turkey Meatloaf w/ Chipotle BBQ"],
    "Sides": ["Satued Broccolini", "Maple Whipped Sweet Potatoes"],
    "Soup": ["Tomato Basil Bisque", "Broccoli Cheddar"],
    "International Station": ["Pasta"]
  },
  "23": {
    "Comfort Food": ["Roasted Italian Chicken Thigh"],
    "Mindful": ["Baked Herbed Cod"],
    "Sides": ["Roasted Vegetables", "Mashed Potatoes"],
    "Soup": ["Tomato Basil Bisque", "Broccoli Cheddar"],
    "International Station": ["Pasta"]
  },
  "26": {
    "Comfort Food": ["Open Faced Pot Roast Sandwich"],
    "Mindful": ["Baked Chicken Parmesan"],
    "Sides": ["Snow Peas", "Pasta"],
    "Soup": ["Italian Wedding", "Cream of Potato"],
    "International Station": ["Burrito"]
  },
  "27": {
    "Comfort Food": ["3 Cheese Penne"],
    "Mindful": ["Biryani Chicken"],
    "Sides": ["Lemon Pepper Green Beans", "Yellow Rice"],
    "Soup": ["Italian Wedding", "Cream of Potato"],
    "International Station": ["Burrito"]
  },
  "28": {
    "Comfort Food": ["Falafel Sandwich Pita/ Tomatoes & Onions"],
    "Mindful": ["Gyro Sandwich/ Pita/ Tomatoes & Onions"],
    "Sides": ["Cucumber Salad", "Tzatziki Sauce", "Lemon Rice"],
    "Soup": ["Italian Wedding", "Cream of Potato"],
    "International Station": ["Burrito"]
  },
  "29": {
    "Comfort Food": ["Fried Chicken"],
    "Mindful": ["Chopped Steak w/ Onion Gravy"],
    "Sides": ["Asparagus", "Scalloped Potatoes"],
    "Soup": ["Italian Wedding", "Cream of Potato"],
    "International Station": ["Burrito"]
  },
  "30": {
    "Comfort Food": ["Turkey Sloppy Joe"],
    "Mindful": ["Dijon Chicken"],
    "Sides": ["Roasted Vegetables", "Mashed Potatoes"],
    "Soup": ["Italian Wedding", "Cream of Potato"],
    "International Station": ["Burrito"]
  }
}
